core_kit/__init__.py
core_kit/db/__init__.py
core_kit/db/db.py
core_kit/db/sessions.py
core_kit/db/settings.py
core_kit/grpc_tools/__init__.py
core_kit/grpc_tools/interseptors/__init__.py
core_kit/grpc_tools/interseptors/request_logger.py
core_kit/grpc_tools/proto/__init__.py
core_kit/grpc_tools/proto/test_service.proto
core_kit/grpc_tools/proto/test_service_pb2.py
core_kit/grpc_tools/proto/test_service_pb2.pyi
core_kit/grpc_tools/proto/test_service_pb2_grpc.py
core_kit/grpc_tools/server.py
core_kit/grpc_tools/servicer.py
core_kit/grpc_tools/settings.py
core_kit/logging_config/__init__.py
core_kit/logging_config/config.py
core_kit/logging_config/settings.py
core_kit/py.typed
core_kit/test_pckg/__init__.py
core_kit/test_pckg/xxx.py
core_kit/utils/__init__.py
core_kit/utils/base.py
core_toolkit-0.1.22.dist-info/METADATA
core_toolkit-0.1.22.dist-info/WHEEL
core_toolkit-0.1.22.dist-info/entry_points.txt
core_toolkit-0.1.22.dist-info/RECORD
