Metadata-Version: 2.1
Name: core-toolkit
Version: 0.1.22
Author: kras
Requires-Python: <4.0,>=3.12
Requires-Dist: sqlalchemy[asyncio,mypy]<3.0.0,>=2.0.36
Requires-Dist: asyncpg[typed]<1.0.0,>=0.30.0
Requires-Dist: pydantic-settings<3.0.0,>=2.6.1
Requires-Dist: pydantic<3.0.0,>=2.10.1
Requires-Dist: python-json-logger<3.0.0,>=2.0.7
Requires-Dist: grpcio<2.0.0,>=1.68.0
Requires-Dist: grpcio-reflection<2.0.0,>=1.68.0
Requires-Dist: grpcio-tools<2.0.0,>=1.68.0
Requires-Dist: protobuf<6.0.0,>=5.28.3
Requires-Dist: grpc-interceptor<1.0.0,>=0.15.4
